api_client/__init__.py
api_client/api_client.py
api_client/http_client.py
api_client/test_api_client.py
rl_api_client-1.0.0.dist-info/METADATA
rl_api_client-1.0.0.dist-info/WHEEL
rl_api_client-1.0.0.dist-info/top_level.txt
rl_api_client-1.0.0.dist-info/RECORD
