Metadata-Version: 2.1
Name: rl-api-client
Version: 1.0.0
Summary: Convenience API Client to use with Redis Enterprise API
Home-page: UNKNOWN
Author: Erez Atiya
Author-email: erez.atiya@redislabs.com
License: UNKNOWN
Platform: UNKNOWN
Classifier: Development Status :: 3 - Alpha
Classifier: Intended Audience :: Developers
Classifier: Programming Language :: Python :: 2.7
Requires-Dist: requests (==2.22.0)
Requires-Dist: urllib3 (==1.25.3)
Requires-Dist: wheel
